latex_project_hw2/__init__.py
latex_project_hw2/latex_generator.py
latex_project_hw2-0.0.1.dist-info/METADATA
latex_project_hw2-0.0.1.dist-info/WHEEL
latex_project_hw2-0.0.1.dist-info/top_level.txt
latex_project_hw2-0.0.1.dist-info/RECORD
