Metadata-Version: 2.2
Name: latex_project_hw2
Version: 0.0.1
Summary: Пакет для генерации LaTeX-кода
Author-email: Алексей Роженко <alexey.rozhenko89@mail.ru>
Requires-Python: >=3.11
